Coolshell20112015Wenji/README.md
Coolshell20112015Wenji/__init__.py
Coolshell20112015Wenji/__main__.py
Coolshell20112015Wenji/file.epub
Coolshell20112015Wenji/index.html
Coolshell20112015Wenji/css/__init__.py
Coolshell20112015Wenji/css/annotations.css
Coolshell20112015Wenji/css/main.css
Coolshell20112015Wenji/css/normalize.css
Coolshell20112015Wenji/css/popup.css
Coolshell20112015Wenji/font/__init__.py
Coolshell20112015Wenji/font/fontello.eot
Coolshell20112015Wenji/font/fontello.svg
Coolshell20112015Wenji/font/fontello.ttf
Coolshell20112015Wenji/font/fontello.woff
Coolshell20112015Wenji/img/__init__.py
Coolshell20112015Wenji/img/annotator-glyph-sprite.png
Coolshell20112015Wenji/img/annotator-icon-sprite.png
Coolshell20112015Wenji/img/apple-touch-icon.png
Coolshell20112015Wenji/img/cancelfullscreen.png
Coolshell20112015Wenji/img/close.png
Coolshell20112015Wenji/img/fullscreen.png
Coolshell20112015Wenji/img/loader.gif
Coolshell20112015Wenji/img/menu-icon.png
Coolshell20112015Wenji/img/save.png
Coolshell20112015Wenji/img/saved.png
Coolshell20112015Wenji/img/settings-s.png
Coolshell20112015Wenji/img/settings.png
Coolshell20112015Wenji/img/star.png
Coolshell20112015Wenji/js/__init__.py
Coolshell20112015Wenji/js/epub.js
Coolshell20112015Wenji/js/epub.min.js
Coolshell20112015Wenji/js/epub.min.map
Coolshell20112015Wenji/js/hooks.min.js
Coolshell20112015Wenji/js/hooks.min.map
Coolshell20112015Wenji/js/reader.js
Coolshell20112015Wenji/js/reader.js.map
Coolshell20112015Wenji/js/reader.min.js
Coolshell20112015Wenji/js/reader.min.map
Coolshell20112015Wenji/js/hooks/__init__.py
Coolshell20112015Wenji/js/hooks/extensions/__init__.py
Coolshell20112015Wenji/js/hooks/extensions/highlight.js
Coolshell20112015Wenji/js/libs/__init__.py
Coolshell20112015Wenji/js/libs/jquery.min.js
Coolshell20112015Wenji/js/libs/localforage.min.js
Coolshell20112015Wenji/js/libs/screenfull.js
Coolshell20112015Wenji/js/libs/screenfull.min.js
Coolshell20112015Wenji/js/libs/zip.min.js
coolshell_2011_2015_wenji-2024.3.2.0.dist-info/METADATA
coolshell_2011_2015_wenji-2024.3.2.0.dist-info/WHEEL
coolshell_2011_2015_wenji-2024.3.2.0.dist-info/entry_points.txt
coolshell_2011_2015_wenji-2024.3.2.0.dist-info/top_level.txt
coolshell_2011_2015_wenji-2024.3.2.0.dist-info/RECORD
